{
	"LocaleSprites": {
		"ui_achievement": ["ui_achievement.png", 18, 150, 42],
		"ui_announcement": ["ui_announcement.png", 2, 202, 154],
		"ui_wave_huge": ["ui_wave_huge.png", 2, 200, 30],
		"ui_readysetcry": ["ui_readysetcry.png", 4, 86, 33],
		"game_over_text": ["game_over_text.png", 1, 290, 29],
		"ui_babies_catalogue": ["ui_babies_catalogue.png", 1, 131, 140],
		"ui_start_button": ["ui_start_button.png", 2, 0, 0],
		"ui_pause_button": ["ui_pause_button.png", 2, 81, 0],
		"ui_continue_button": ["ui_continue_button.png", 2, 126, 62],
		"ui_item_soldout": ["ui_item_soldout.png", 1, 12, 0],
	},

	               "goodNews": "好消息！",
                          "newUpdate1": "一个新的更新已经发布##",
                          "newUpdate2": "打开下载页",
                          "newUpdate3": "不，我很好",
                          "disclaimer1": "警告！",
                          "disclaimer2": "如果你看到此消息，你可能并没有安装 DirectX 9.0c # 我强烈建议安装此程序 #  这样游戏才能以最佳渲染方式运行。 ",
                          "disclaimer3": "按任意键继续",
                          "chooseCard": "选择一张卡添加到你的进程中。",
                          "reroll": "重置",
                          "unknown": "未知",
                          "wasntEncountered": "还没遇到过",
                          "chooseActive": "主动道具（只能携带一个）",
                          "gamePaused": "游戏暂停",
                          "gamePausedContinue": "继续",
                          "gamePausedRestart": "重新开始",
                          "gameSettingMusic": "音乐大小",
                          "gameSettingSound": "音效大小",
                          "gameSettingMusicSpeed1": "音乐速度：跟随游戏速度",
                          "gameSettingMusicSpeed2": "音乐速度：保持恒定",
                          "gameSettingFlashingEffectsOn": "闪烁效果：开",
                          "gameSettingFlashingEffectsOff": "闪烁效果：关",
                          "gameSettingFullscreen": "显示模式：窗口",
                          "gameSettingLanguage": "语言：简体中文",
                          "gamePausedQuit": "退出游戏",
                          "gameSettingWindowMode": "显示模式：全屏",
                          "gamePausedNewRun": "新游戏",
                          "gamePausedStats": "统计数据",
                          "gamePausedAchievements": "成就",
                          "gamePausedCollection": "收集",
                          "gamePausedStuff": "道具",
                          "gamePausedRetry": "重试",
                          "gamePausedQuitToMenu": "退出到菜单",
                          "gamePausedBack": "返回",
                          "gamePausedSettings": "选项",
                          "file": "档案",
                          "fileSelect": "选择存档",
                          "gameMode1": "普通模式",
                          "gameMode2": "困难模式",
                          "gameMode3": "挑战模式",
                          "gameMode1Description": "这儿没什么特殊的",
                          "gameMode2Description": "增加难度，限制红心，更多的敌人以及奖励",
                          "gameMode2DescriptionLocked": "在一局游戏中循环两次解锁",
                          "gameMode3Description": "更多玩法",
                          "gameMode3DescriptionLocked": "完成每一章节解锁",
                          "gamePausedDescriptionRestart": "或摁住R键（所有的进度都会丢失！）",
                          "gameSettingDescriptionSound": "使用左键和右键去调整音量大小",
                          "gameSettingDescriptionFullscreen": "或使用F键进行切换",
                          "gamePausedDescription6": "语言：简体中文",
                          "gamePausedDescriptionQuitToMenu": "摁住以退出（你的进度已经保存）",
                          "gamePausedSocialTwitter": "注销账号(在Twitter上)",
                          "gamePausedSocialDiscord": "发送威胁消息 (在Discord上)",
                          "gamePausedDescriptionAchievements": "使用鼠标滑轮向上/向下滚动",
                          "gameSettingCardStyleVertical": "卡槽样式：竖直",
                          "gameSettingCardStyleHorizontal": "卡槽样式：水平",
                          "gameSettingDescriptionCardStyle": "影响卡槽的排列方式",
                          "statsUnlockedContent": "已解锁内容：",
                          "statsKilledEnemies": "击败的敌人：",
                          "statsGigaPlum": "击败的梅子宝宝：",
                          "statsRagdoll": "击败的绷带巫毒娃娃：",
                          "statsMiddleHorn": "击败的中角：",
                          "statsDeaths": "游戏失败：",
                          "statsUsedPills": "使用的药丸：",
                          "loopRecords": "最长的循环：",
                          "eraseAllData": "清除全部数据 ",
                          "gameOverMessage0": "这不是你的错...",
                          "gameOverMessage1": "这不公平, 也不正义...",
                          "gameOverMessage2": "没有时间流眼泪了...",
                          "gameOverMessage3": "现在还不能放弃...",
                          "gameOverMessage4": "我们明天还能一起玩, 对吗？",
                          "gameOverMessage5": "他们会为此买单...",
                          "gameOverMessage6": "而你不会赢得奖杯。",
                          "gameOverMessage7": "她不配拥有你。",
                          "gameOverMessage8": "这只是噩梦...",
                          "gameOverMessage9": "现在怎么办？",
                          "gameOverMessage10": "这游戏糟透了。",
                          "gameOverMessage11": "没关系，别害怕...",
                          "gameOverMessage12": "这只是一场游戏，对吧？",
                          "gameOverMessage13": "不会那么糟的...",
                          "gameOverMessage14": "继续尝试...",
                          "gameOverMessage15": "接下来呢？",
                          "gameOverMessage16": "这似曾相识...",
                          "gameOverMessage17": "休息一会...",
                          "gameOverMessage18": "太突然了...",
                          "achievementDetails0": "打碎30块琥珀块",
                          "achievementDetails1": "放置两列尖刺宝宝",
                          "achievementDetails2": "喂一个宝宝吃三颗药丸",
                          "achievementDetails3": "解除炸弹棉花怪的炸弹",
                          "achievementDetails4": "一次爆炸消灭10个敌人",
                          "achievementDetails5": "用影之书保护迷失游魂",
                          "achievementDetails6": "在卡槽中只有红色宝宝#完成任意关卡",
                          "achievementDetails7": "不使用生产红心的宝宝#完成每一章节",
                          "achievementDetails8": "只选择隐藏起来的宝宝#完成每一章节",
                          "achievementDetails9": "不使用主动道具#完成每一章节",
                          "achievementDetails10": "不失去任何冲锋怪#完成每一章节",
                          "achievementDetails11": "完成挑战 1",
                          "achievementDetails12": "完成挑战 2",
                          "achievementDetails13": "完成挑战 3",
                          "achievementDetails14": "完成挑战 4",
                          "achievementDetails15": "完成挑战 5",
                          "achievementDetails16": "完成挑战 6",
                          "achievementDetails17": "完成褐色仪式",
                          "challengeLocked": "完成其他挑战解锁",
                          "challenges1": "速度节屁",
                          "challenges2": "无宝配合",
                          "challenges3": "卧槽?",
                          "challenges4": "内战",
                          "challenges5": "受限版",
                          "challenges6": "俄罗斯方块",
                          "shapeShifterRotate": "使用鼠标滑轮向上/向下（或Q/E键）以旋转形状",
                          "it1name0": "红铲子",
                          "it1name1": "冠军腰带",
                          "it1name2": "小药袋",
                          "it1name3": "发条钥匙",
                          "it1name4": "伊甸的祝福",
                          "it1name5": "<3",
                          "it1name6": "更多选择",
                          "it1name7": "蜘蛛模组",
                          "it1name8": "水晶球",
                          "it1name9": "邪眼护符",
                          "it1name10": "紫心奖章",
                          "it1name11": "龌龊之心",
                          "it1name12": "冰霜薄荷糖",
                          "it1name13": "神秘礼物",
                          "it1name14": "豆子",
                          "it1name15": "医学博士",
                          "it1name16": "毛毯",
                          "it1name17": "锋利插头",
                          "it1name18": "以撒的叉子",
                          "it1name19": "翻转",
                          "it1name20": "六面骰",
                          "it1name21": "怀表",
                          "it1name22": "额外选择",
                          "it2name0": "蓄电池",
                          "it2name1": "Steam大促",
                          "it2name2": "书包",
                          "it2name3": "药学博士证",
                          "it2name4": "宝可Go",
                          "it2name5": "救恩",
                          "it2name6": "血色羁绊",
                          "it2name7": "黑豆",
                          "itChargerToken": "冲锋怪复位信物",
                          "itChargerTokenDescription": "允许你重置一只已经使用的冲锋怪",
                          "itActiveName0": "影之书",
                          "itActiveName1": "胎儿博士的遥控器",
                          "itActiveName2": "大便",
                          "itActiveName3": "心灵感应傻瓜式教程",
                          "itActiveName4": "怪物手册",
                          "itActiveName5": "祭坛",
                          "itActiveName6": "腰豆",
                          "itActiveName7": "友好球",
                          "itActiveName8": "发光沙漏",
                          "itActiveName9": "搬家盒",
                          "itActiveName10": "红蜡烛",
                          "itActiveName11": "蓝蜡烛",
                          "itActiveName12": "残损铁镐",
                          "itActiveName13": "雪花玻璃球",
                          "itActiveName14": "生命之息",
                          "itActiveName15": "糖心",
                          "it1description0": "拿回属于你的东西",
                          "it1description1": "每层都有更多波次",
                          "it1description2": "允许拥有四颗药丸",
                          "it1description3": "手动启动",
                          "it1description4": "你的未来更加光明",
                          "it1description5": "开局红心更多",
                          "it1description6": "额外选择",
                          "it1description7": "贾维斯，给我看看他们的血条吧",
                          "it1description8": "显示隐藏的选项",
                          "it1description9": "显示怪物从哪里进攻",
                          "it1description10": "增加遇到精英敌人的几率",
                          "it1description11": "肮脏伙伴",
                          "it1description12": "冻结攻击你的宝宝的敌人",
                          "it1description13": "为你精心包装！",
                          "it1description14": "宝宝被杀时会放屁，把敌人推回去",
                          "it1description15": "允许你更换受伤的宝宝",
                          "it1description16": "最内侧一列的宝宝有一个保护泡",
                          "it1description17": "当宝宝被攻击时，相应的卡获得充能",
                          "it1description18": "用尖刺或荆棘杀死的敌人会掉落红心",
                          "it1description19": "右击可使宝宝转身",
                          "it1description20": "重置你的命运",
                          "it1description21": "稍微调慢一点...",
                          "it1description22": "击败BOSS有两个奖励，但只能拿一个",
                          "it2description0": "储存充能",
                          "it2description1": "商店提供33%的折扣",
                          "it2description2": "允许多带一个宝宝",
                          "it2description3": "更好的药丸，更多的知识",
                          "it2description4": "在关卡开始时给你一张随机的怪物卡",
                          "it2description5": "在紧急情况下消灭整行敌人，为你节省一个冲锋怪",
                          "it2description6": "在你的防御型宝宝面前生成尖刺",
                          "it2description7": "新放置的宝宝会放屁，使附近敌人中毒",
                          "itActiveDescription0": "给予保护光环",
                          "itActiveDescription1": "充能型空袭",
                          "itActiveDescription2": "一坨屎",
                          "itActiveDescription3": "你也该学学了",
                          "itActiveDescription4": "随机性生成伙伴",
                          "itActiveDescription5": "他寻求献祭",
                          "itActiveDescription6": "魅惑屁！",
                          "itActiveDescription7": "收服所有怪物吧！",
                          "itActiveDescription8": "逆转时间",
                          "itActiveDescription9": "打包再拆包",
                          "itActiveDescription10": "消灭一整行怪物",
                          "itActiveDescription11": "消灭一整列怪物",
                          "itActiveDescription12": "可以摧毁障碍",
                          "itActiveDescription13": "暂时冻结屏幕上的所有敌人",
                          "itActiveDescription14": "让倒下的宝宝复活",
                          "itActiveDescription15": "献祭你的主动道具栏位，开局红心更多",
                          "pillName0": "大力丸！！！",
                          "pillName1": "速度下降",
                          "pillName2": "速度提升",
                          "pillName3": "体力回满",
                          "pillName4": "哪里不对...",
                          "pillName5": "止痛药！",
                          "cardName0": "???",
                          "cardName1": "击杀",
                          "cardName2": "波比弟弟",
                          "cardName3": "查德宝宝",
                          "cardName4": "肉块",
                          "cardName5": "鲍勃的脑浆子",
                          "cardName6": "小洛基",
                          "cardName7": "小丑宝宝",
                          "cardName8": "巫师宝宝",
                          "cardName9": "冰冻宝宝",
                          "cardName10": "圣地大便",
                          "cardName11": "大美蝇",
                          "cardName12": "放屁宝宝",
                          "cardName13": "蒙戈宝宝",
                          "cardName14": "史蒂文宝宝",
                          "cardName15": "多维宝宝",
                          "cardName16": "蜘蛛宝宝",
                          "cardName17": "彩虹宝宝",
                          "cardName18": "橡胶灵魂",
                          "cardName19": "幽灵宝宝",
                          "cardName20": "尖刺宝宝",
                          "cardName21": "神秘的卵",
                          "cardName22": "恶魔宝宝",
                          "cardName23": "肉中刺",
                          "cardName24": "毒瘾宝宝",
                          "cardName25": "亚伯",
                          "cardName26": "枯骨宝宝",
                          "cardName27": "返生者",
                          "cardName28": "焦酥宝宝",
                          "cardName29": "逾越节蜡烛",
                          "cardName30": "飞马座",
                          "cardName31": "雪球",
                          "cardName32": "迷失游魂",
                          "cardName33": "连体宝宝",
                          "cardName34": "瘘管",
                          "cardName35": "粘液卵囊",
                          "cardName36": "灵能宝宝",
                          "cardName37": "窥眼",
                          "cardName38": "小鬼",
                          "cardName39": "魔王宝宝",
                          "cardName40": "拟寄生物",
                          "cardName41": "脑虫",
                          "cardName42": "绷带球",
                          "cardName999": "神秘礼物",
                          "cardDescription2": "最初的防御手段，向进攻的怪物发射眼泪",
                          "cardDescription3": "产生额外的红心",
                          "cardDescription4": "具有很高的抗性，可以用来保护其他宝宝",
                          "cardDescription5": "一接触就爆炸，但需要时间长大",
                          "cardDescription6": "把眼泪射向四个基本方向",
                          "cardDescription7": "向相邻的两条路射出眼泪，但是无法保护自己",
                          "cardDescription8": "朝两个对角方向射出眼泪，但是无法保护自己",
                          "cardDescription9": "射出冰冻眼泪，让敌人难以前进",
                          "cardDescription10": "提高3×3区域内其他宝宝的速度和生产速度",
                          "cardDescription11": "放置时爆炸，炸毁3x3区域的怪物",
                          "cardDescription12": "将敌人转移到其他路上",
                          "cardDescription13": "模仿背后宝宝的射击风格",
                          "cardDescription14": "射出跟踪眼泪，能瞄准相邻路上的敌人",
                          "cardDescription15": "复制穿过它的射弹",
                          "cardDescription16": "投掷蜘蛛卵，减缓敌人的速度",
                          "cardDescription17": "射击随机效果眼泪",
                          "cardDescription18": "投掷能从一个敌人反弹到另一个敌人的橡胶球",
                          "cardDescription19": "发射能伤害多个敌人的幽灵眼泪",
                          "cardDescription20": "伤害任何踩在上面的敌人",
                          "cardDescription21": "通过释放被魅惑的怪物来保护防线",
                          "cardDescription22": "向5x5区域内所有附近的敌人射出眼泪",
                          "cardDescription23": "防御，同时对攻击它的敌人造成伤害",
                          "cardDescription24": "在附近3×3区域内的宝宝之间共享药丸效果",
                          "cardDescription25": "在相反的方向创建一个复制幻影",
                          "cardDescription26": "提供保护，死亡时爆炸",
                          "cardDescription27": "喷火，伤害6个相邻地块中的怪物",
                          "cardDescription28": "沿路发射火球",
                          "cardDescription29": "把经过的眼泪变成爆炸的火球",
                          "cardDescription30": "制造出一股风把敌人吹走",
                          "cardDescription31": "瞬间冻结3x6区域的怪物",
                          "cardDescription32": "保护他，他会给你回报",
                          "cardDescription33": "给的红心是小查德的两倍",
                          "cardDescription34": "当它的护甲被摧毁时，它会冲下防线，咬住敌人",
                          "cardDescription35": "提供保护并减缓附近怪物的速度",
                          "cardDescription36": "能击中当前路上最多三个目标，两次！",
                          "cardDescription37": "向视野中离房间最近的目标喷射血块",
                          "cardDescription38": "无成本的短程射手！",
                          "cardDescription39": "射出火球，从被击败的敌人中制造出友好的小鬼",
                          "cardDescription40": "射出卵泪，分裂成友好的苍蝇",
			  "cardDescription41": "他们的眼泪会以90度角向无法击中的敌人飞去",
			  "cardDescription42": "保护其他宝宝，从附近的路线吸引敌人",
                          "cardDescription999": "点击打开包装",
                          "stageName1": "淹水地下室 I",
                          "stageName2": "淹水地下室 II",
                          "stageName3": "淹水地下室 III",
                          "stageName4": "Boss!",
                          "stageName5": "墓穴矿坑 I",
                          "stageName6": "墓穴矿坑 II",
                          "stageName7": "墓穴矿坑 III",
                          "stageName8": "Boss!",
                          "stageName9": "方舟陵墓 I",
                          "stageName10": "方舟陵墓 II",
                          "stageName11": "方舟陵墓 III",
                          "stageName12": "Boss!",
                          "enemyName0": "裂口尸",
                          "enemyName1": "苍蝇",
                          "enemyName2": "肥仔",
                          "enemyName3": "梅子",
                          "enemyName4": "跳蛛",
                          "enemyName5": "咬咬寄生虫",
                          "enemyName6": "皱眉裂口尸",
                          "enemyName7": "寄居骷髅",
                          "enemyName8": "炸弹棉花怪",
                          "enemyName9": "粪团",
                          "enemyName10": "石肥仔",
                          "enemyName11": "虚影恶魔",
                          "enemyName12": "冰霜邪教徒",
                          "enemyName13": "化石粪堆",
                          "enemyName14": "贪吃鲸魂",
                          "enemyName15": "巨型梅子",
                          "enemyName16": "老妈的手",
                          "enemyName17": "绷带巫毒人偶",
                          "enemyName18": "害羞先生",
                          "enemyName19": "中角",
                          "enemyDescription0": "一个普通的敌人怪物",
                          "enemyDescription1": "攻击你的防御性宝宝时，会对它们自己造成伤害",
                          "enemyDescription2": "放屁，把敌人推到其他路线",
                          "enemyDescription3": "飞过障碍物，而不是攻击它们",
                          "enemyDescription4": "从一个格子跳到另一个格子，每次都会换线",
                          "enemyDescription5": "藏在地下，咬人时钻出",
                          "enemyDescription6": "连续攻击最后一个可附着的婴儿",
                          "enemyDescription7": "它坚硬的头骨使它免受来自上方的任何伤害",
                          "enemyDescription8": "在接触时爆炸",
			  "enemyDescription9": "快速猛冲，推动障碍物，冲击你的防御",
			  "enemyDescription10": "吸引附近其他路线的敌人",
			  "enemyDescription11": "大多数时候看不见",
			  "enemyDescription12": "发射冷冻射弹",
			  "enemyDescription13": "冲锋，将宝宝和障碍物进一步推向左侧",
			  "enemyDescription14": "他一口就能吃下任何东西，然后马上离开",
			  "enemyDescription15": "一个真的非常大的梅子",
			  "enemyDescription16": "想偷你的宝宝",
			  "enemyDescription17": "所有绷带巫毒生物的女王",
			  "enemyDescription18": "他的面具保护他免受负面影响和批评",
			  "enemyDescription19": "这点我甚至不知道"
}